Metadata-Version: 2.1
Name: eidawsauth
Version: 0.3.1
Summary: Implement /auth for EIDA
Home-page: https://gitlab.com/resif/ws-eidaauth
Author: Jonathan Schaeffer
Author-email: jonathan.schaeffer@univ-grenoble-alpes.fr
Maintainer: Jonathan Schaeffer
Maintainer-email: jonathan.schaeffer@univ-grenoble-alpes.fr
License: GPL-3.0
Platform: UNKNOWN
Classifier: Development Status :: 4 - Beta
Classifier: Intended Audience :: Developers
Classifier: License :: OSI Approved :: GNU General Public License v3 or later (GPLv3+)
Classifier: Natural Language :: English
Classifier: Operating System :: OS Independent
Classifier: Programming Language :: Python :: 3.6
Classifier: Programming Language :: Python :: 3.7
